{
    "room": {
        "w": 10,
        "l": 10,
        "h": 10
    },
    "obstacles": [
        {
            "id": 0,
            "position": [
                -3.4972983295439044,
                -2.779961702738735,
                0.2
            ],
            "orientation": [
                0.0,
                0.0,
                0.7727951935910762,
                0.6346554882473887
            ],
            "color_rgba": [
                0,
                0,
                1,
                1
            ]
        },
        {
            "id": 1,
            "position": [
                1.8558856738256413,
                -3.93997420264361,
                0.2
            ],
            "orientation": [
                0.0,
                0.0,
                0.6199682404765239,
                0.7846269054782936
            ],
            "color_rgba": [
                1,
                0.75,
                0.8,
                1
            ]
        },
        {
            "id": 2,
            "position": [
                0.5238389612895737,
                3.940126723125239,
                0.2
            ],
            "orientation": [
                0.0,
                0.0,
                0.8476210406558105,
                0.5306020838986225
            ],
            "color_rgba": [
                1,
                0.64,
                0,
                1
            ]
        },
        {
            "id": 3,
            "position": [
                -1.2914704974960696,
                -3.5730121656214524,
                0.2
            ],
            "orientation": [
                0.0,
                0.0,
                0.9654561490317906,
                0.26056558540356967
            ],
            "color_rgba": [
                1,
                1,
                0,
                1
            ]
        },
        {
            "id": 4,
            "position": [
                1.9277338790423402,
                -0.47250499396174206,
                0.2
            ],
            "orientation": [
                0.0,
                0.0,
                0.9119908838057829,
                0.41021046775423375
            ],
            "color_rgba": [
                0,
                0,
                0,
                1
            ]
        }
    ],
    "table": {
        "position": [
            3.7453997609218685,
            -3.2637097621463314,
            0
        ],
        "orientation": [
            0.0,
            0.0,
            -0.5144150522991923,
            0.8575413424249698
        ],
        "size": [
            1.5,
            0.8
        ]
    }
}